{"logs": [{"code": 123, "message": "example", "additional": "example2", "time": "2023-02-22 16:23:38.614720"}, {"code": 123, "message": "asdfjsd", "additional": "kajsdfkasdj", "time": "2023-02-22 16:26:48.875912"}, {"code": 123, "message": "asdfjsd", "additional": "kajsdfkasdj", "time": "2023-02-22 16:26:51.882656"}, {"code": 123, "message": "asdfjsd", "additional": "kajsdfkasdj", "time": "2023-02-22 16:26:54.601732"}, {"code": 123, "message": "asdfjsd", "additional": "kajsdfkasdj", "time": "2023-02-22 16:26:57.984438"}, {"code": 123, "message": "asdfjsd", "additional": "kajsdfkasdj", "time": "2023-02-22 16:27:00.750945"}, {"code": 123, "message": "asdfjsd", "additional": "kajsdfkasdj", "time": "2023-02-22 16:27:03.612736"}, {"code": 123, "message": "asdfjsd", "additional": "kajsdfkasdj", "time": "2023-02-22 16:28:32.613262"}, {"code": 123, "message": "asdfjsd", "additional": "kajsdfkasdj", "time": "2023-02-22 16:28:37.094457"}, {"code": 123, "message": "asdfjsd", "additional": "kajsdfkasdj", "time": "2023-02-22 16:28:40.064843"}, {"code": 123, "message": "asdfjsd", "additional": "kajsdfkasdj", "time": "2023-02-22 16:28:42.581269"}, {"code": 123, "message": "asdfjsd", "additional": "kajsdfkasdj", "time": "2023-02-22 16:31:37.023188"}, {"code": 123, "message": "asdfjsd", "additional": "kajsdfkasdj", "time": "2023-02-22 16:36:04.637783"}, {"code": 123, "message": "asdfjsd", "additional": "kajsdfkasdj", "time": "2023-02-22 16:36:09.368411"}, {"code": 123, "message": "asdfjsd", "additional": "kajsdfkasdj", "time": "2023-02-22 16:36:11.858993"}, {"code": 123, "message": "asdfjsd", "additional": "kajsdfkasdj", "time": "2023-02-22 16:36:15.744641"}, {"code": 123, "message": "asdfjsd", "additional": "kajsdfkasdj", "time": "2023-02-22 16:36:19.689373"}, {"code": 123, "message": "asdfjsd", "additional": "kajsdfkasdj", "time": "2023-02-22 16:36:22.182983"}, {"code": 123, "message": "asdfjsd", "additional": "kajsdfkasdj", "time": "2023-02-22 16:36:32.809670"}, {"code": 123, "message": "asdfjsd", "additional": "kajsdfkasdj", "time": "2023-02-22 16:36:38.275921"}, {"code": 123, "message": "asdfjsd", "additional": "kajsdfkasdj", "time": "2023-02-22 16:36:42.265295"}, {"code": 123, "message": "asdfjsd", "additional": "kajsdfkasdj", "time": "2023-02-22 16:36:47.797324"}, {"code": 123, "message": "asdfjsd", "additional": "kajsdfkasdj", "time": "2023-02-22 16:36:50.252207"}, {"code": 123, "message": "asdfjsd", "additional": "kajsdfkasdj", "time": "2023-02-22 16:36:53.516890"}, {"code": 123, "message": "asdfjsd", "additional": "kajsdfkasdj", "time": "2023-02-22 17:04:43.315988"}]}